all_in_mcp/__init__.py
all_in_mcp/server.py
apaper/__init__.py
apaper/server.py
apaper/models/__init__.py
apaper/models/paper.py
apaper/platforms/__init__.py
apaper/platforms/base.py
apaper/platforms/dblp.py
apaper/platforms/google_scholar.py
apaper/platforms/iacr.py
apaper/utils/__init__.py
qwen_search/__init__.py
qwen_search/server.py
all_in_mcp-0.4.2.dist-info/METADATA
all_in_mcp-0.4.2.dist-info/WHEEL
all_in_mcp-0.4.2.dist-info/entry_points.txt
all_in_mcp-0.4.2.dist-info/licenses/LICENSE
all_in_mcp-0.4.2.dist-info/RECORD
