Metadata-Version: 2.4
Name: all-in-mcp
Version: 0.4.2
Summary: An MCP (Model Context Protocol) server providing daily-use utility functions and academic paper search capabilities
Project-URL: Homepage, https://github.com/jiahaoxiang2000/all-in-mcp
Project-URL: Repository, https://github.com/jiahaoxiang2000/all-in-mcp
Project-URL: Documentation, https://github.com/jiahaoxiang2000/all-in-mcp/tree/main/docs
Project-URL: Issues, https://github.com/jiahaoxiang2000/all-in-mcp/issues
Author-email: isomo <jiahaoxiang2000@gmail.com>
License: MIT
License-File: LICENSE
Keywords: academic,iacr,mcp,model-context-protocol,papers,utilities
Classifier: Development Status :: 4 - Beta
Classifier: Intended Audience :: Developers
Classifier: Intended Audience :: Science/Research
Classifier: License :: OSI Approved :: MIT License
Classifier: Programming Language :: Python :: 3
Classifier: Programming Language :: Python :: 3.10
Classifier: Programming Language :: Python :: 3.11
Classifier: Programming Language :: Python :: 3.12
Classifier: Programming Language :: Python :: 3.13
Classifier: Topic :: Scientific/Engineering
Classifier: Topic :: Software Development :: Libraries :: Python Modules
Classifier: Topic :: Text Processing :: General
Requires-Python: >=3.10
Requires-Dist: beautifulsoup4>=4.12.0
Requires-Dist: fastmcp>=2.11.3
Requires-Dist: httpx>=0.24.0
Requires-Dist: pypdf>=4.0.0
Requires-Dist: requests>=2.31.0
Provides-Extra: dev
Requires-Dist: build>=1.0.0; extra == 'dev'
Requires-Dist: mypy>=1.5.0; extra == 'dev'
Requires-Dist: ruff>=0.1.0; extra == 'dev'
